supersolids/Schroedinger.py
supersolids/__init__.py
supersolids/__main__.py
supersolids/Animation/Animation.py
supersolids/Animation/MatplotlibAnimation.py
supersolids/Animation/MayaviAnimation.py
supersolids/Animation/__init__.py
supersolids/helper/Box.py
supersolids/helper/Resolution.py
supersolids/helper/__init__.py
supersolids/helper/constants.py
supersolids/helper/cut_1d.py
supersolids/helper/functions.py
supersolids/helper/get_path.py
supersolids/helper/run_time.py
supersolids/helper/simulate_case.py
supersolids/scripts/__init__.py
supersolids/scripts/cp_plots.py
supersolids/scripts/density_in_trap.py
supersolids/scripts/flycheck_multi_simulate.py
supersolids/scripts/multi_load.py
supersolids/scripts/multi_property.py
supersolids/scripts/multi_simulate.py
supersolids/scripts/multi_simulate_real.py
supersolids/scripts/plotting.py
supersolids/scripts/deprecated/__init__.py
supersolids/scripts/deprecated/multi_core.py
supersolids/scripts/deprecated/single_core.py
supersolids/tools/__init__.py
supersolids/tools/get_System_at_npz.py
supersolids/tools/load_npz.py
supersolids/tools/simulate_npz.py
supersolids/tools/track_property.py
supersolids-0.1.33.dist-info/LICENSE.rst
supersolids-0.1.33.dist-info/METADATA
supersolids-0.1.33.dist-info/WHEEL
supersolids-0.1.33.dist-info/top_level.txt
supersolids-0.1.33.dist-info/RECORD
