Metadata-Version: 2.1
Name: supersolids
Version: 0.1.33
Summary: Simulate and animate supersolids.
Home-page: https://github.com/Scheiermann/supersolids
Author: Scheiermann
Author-email: daniel.scheiermann@stud.uni-hannover.de
License: MIT
Platform: UNKNOWN
Requires-Python: >=3.6
License-File: LICENSE.rst
Requires-Dist: dill
Requires-Dist: ffmpeg-python
Requires-Dist: matplotlib
Requires-Dist: numpy
Requires-Dist: mayavi
Requires-Dist: psutil
Requires-Dist: pyqt5
Requires-Dist: scipy
Requires-Dist: sphinx-autoapi
Requires-Dist: sphinx-rtd-theme
